README
setup.py
OrbitalPy.egg-info/PKG-INFO
OrbitalPy.egg-info/SOURCES.txt
OrbitalPy.egg-info/dependency_links.txt
OrbitalPy.egg-info/requires.txt
OrbitalPy.egg-info/top_level.txt
orbital/__init__.py
orbital/bodies.py
orbital/constants.py
orbital/elements.py
orbital/maneuver.py
orbital/plotting.py
orbital/utilities.py